pelican/plugins/similar_posts/__init__.py
pelican/plugins/similar_posts/similar_posts.py
pelican/plugins/similar_posts/test_similar_posts.py
pelican_similar_posts-1.0.0.dist-info/LICENSE
pelican_similar_posts-1.0.0.dist-info/WHEEL
pelican_similar_posts-1.0.0.dist-info/METADATA
pelican_similar_posts-1.0.0.dist-info/RECORD
