Metadata-Version: 2.1
Name: pelican-similar-posts
Version: 1.0.0
Summary: Pelican plugin to add similar posts to articles, based on a vector space model
Home-page: https://github.com/pelican-plugins/similar-posts
License: GPL-3.0-only
Keywords: pelican,plugin,similarity,tf-idf,tags,gensim,vector-space-model,algebraic-model,numpy,scipy
Author: David Lesieur
Author-email: david@davidlesieur.com
Requires-Python: >=3.6,<4.0
Classifier: Development Status :: 5 - Production/Stable
Classifier: Environment :: Console
Classifier: Framework :: Pelican
Classifier: Framework :: Pelican :: Plugins
Classifier: Intended Audience :: End Users/Desktop
Classifier: License :: OSI Approved :: GNU General Public License v3 (GPLv3)
Classifier: Operating System :: OS Independent
Classifier: Programming Language :: Python :: 3
Classifier: Programming Language :: Python :: 3.6
Classifier: Programming Language :: Python :: 3.7
Classifier: Programming Language :: Python :: 3.8
Classifier: Programming Language :: Python :: 3.9
Classifier: Topic :: Internet :: WWW/HTTP
Classifier: Topic :: Scientific/Engineering :: Information Analysis
Classifier: Topic :: Software Development :: Libraries :: Python Modules
Classifier: Topic :: Text Processing :: Indexing
Provides-Extra: markdown
Requires-Dist: gensim (>=3.5.0)
Requires-Dist: markdown (>=3.2.2,<4.0.0); extra == "markdown"
Requires-Dist: pelican (>=4.5,<5.0)
Project-URL: Documentation, https://docs.getpelican.com
Project-URL: Funding, https://donate.getpelican.com/
Project-URL: Issue Tracker, https://github.com/pelican-plugins/similar-posts/issues
Project-URL: Repository, https://github.com/pelican-plugins/similar-posts
